keepassxc_run/__init__.py
keepassxc_run/__main__.py
keepassxc_run/cli.py
keepassxc_run/process.py
keepassxc_run/secret.py
keepassxc_run-0.1.0.dist-info/METADATA
keepassxc_run-0.1.0.dist-info/WHEEL
keepassxc_run-0.1.0.dist-info/entry_points.txt
keepassxc_run-0.1.0.dist-info/licenses/LICENSE
keepassxc_run-0.1.0.dist-info/RECORD
