Metadata-Version: 2.4
Name: keepassxc-run
Version: 0.1.0
Summary: KeePassXC runner
Project-URL: homepage, https://github.com/kai2nenobu/keepassxc-run
Project-URL: documentation, https://github.com/kai2nenobu/keepassxc-run#keepassxc-run
Project-URL: changelog, https://github.com/kai2nenobu/keepassxc-run/blob/main/CHANGELOG.md
Project-URL: source, https://github.com/kai2nenobu/keepassxc-run
Project-URL: issues, https://github.com/kai2nenobu/keepassxc-run/issues
Author-email: Tsunenobu Kai <kai2nenobu@gmail.com>
License: MIT License
License-File: LICENSE
Keywords: keepassxc
Classifier: Development Status :: 3 - Alpha
Classifier: Intended Audience :: Developers
Classifier: License :: OSI Approved :: MIT License
Classifier: Programming Language :: Python
Classifier: Programming Language :: Python :: 3
Classifier: Programming Language :: Python :: 3.9
Classifier: Programming Language :: Python :: 3.10
Classifier: Programming Language :: Python :: 3.11
Classifier: Programming Language :: Python :: 3.12
Classifier: Programming Language :: Python :: 3.13
Classifier: Topic :: Security
Classifier: Topic :: Utilities
Requires-Python: >=3.9
Requires-Dist: python-dotenv>=1.0.1
